[
    {
        "artistName": "Ben Fuller"
    },
    {
        "artistName": "Brandon Lake"
    },
    {
        "artistName": "Brennley Brown"
    },
    {
        "artistName": "CAIN"
    },
    {
        "artistName": "CASTING CROWNS"
    },
    {
        "artistName": "Chris Ekiss"
    },
    {
        "artistName": "David Leonard"
    },
    {
        "artistName": "DOE"
    },
    {
        "artistName": "KB"
    },
    {
        "artistName": "LEANNA CRAWFORD"
    },
    {
        "artistName": "Lizzie Morgan"
    },
    {
        "artistName": "MATT MAHER"
    },
    {
        "artistName": "MATTHEW WEST"
    },
    {
        "artistName": "RED ROCKS WORSHIP"
    },
    {
        "artistName": "Ryan Ellis"
    },
    {
        "artistName": "Seph Schlueter"
    },
    {
        "artistName": "SEU WORSHIP"
    },
    {
        "artistName": "Steffany Gretzinger"
    },
    {
        "artistName": "ZACH WILLIAMS"
    }
]